fice_client/__init__.py
fice_client/api/__init__.py
fice_client/api/agents_api.py
fice_client/api/authorization_api.py
fice_client/api/compliance_api.py
fice_client/api/compliance_policy_api.py
fice_client/api/devices_api.py
fice_client/api/miscellaneous_api.py
fice_client/api/tenats_api.py
fice_client/api_client.py
fice_client/api_response.py
fice_client/configuration.py
fice_client/exceptions.py
fice_client/models/__init__.py
fice_client/models/agent.py
fice_client/models/agent_cmd.py
fice_client/models/agent_with_status.py
fice_client/models/code_rule_definition.py
fice_client/models/compliance_log.py
fice_client/models/compliance_policy.py
fice_client/models/compliance_report.py
fice_client/models/device.py
fice_client/models/device_config.py
fice_client/models/http_validation_error.py
fice_client/models/info.py
fice_client/models/kind.py
fice_client/models/line_range.py
fice_client/models/location_inner.py
fice_client/models/new_agent.py
fice_client/models/new_command.py
fice_client/models/new_compliance_failure.py
fice_client/models/new_compliance_policy.py
fice_client/models/new_device.py
fice_client/models/new_tenant.py
fice_client/models/outcome.py
fice_client/models/rule.py
fice_client/models/rule_with_input_context.py
fice_client/models/severity.py
fice_client/models/simple_rule.py
fice_client/models/tenant.py
fice_client/models/user_and_agent.py
fice_client/models/validation_error.py
fice_client/py.typed
fice_client/rest.py
fice_client-1.0.0.dist-info/METADATA
fice_client-1.0.0.dist-info/WHEEL
fice_client-1.0.0.dist-info/RECORD
